lxnet_navigator/__init__.py
lxnet_navigator/analyze_lxnet.py
lxnet_navigator/convert_lxnet.py
lxnet_navigator/create_lxnet.py
lxnet_navigator-1.0.1.dist-info/METADATA
lxnet_navigator-1.0.1.dist-info/WHEEL
lxnet_navigator-1.0.1.dist-info/top_level.txt
lxnet_navigator-1.0.1.dist-info/RECORD
