Metadata-Version: 2.1
Name: lxnet-navigator
Version: 1.0.1
Summary: For Private Use
Home-page: 
Download-URL: https://pypi.org/project/lxnet_navigator/
Author: Bruce W Lee
Author-email: woongsung.lee@gmail.com
License: Unlicensed
Keywords: WordNet
Requires-Dist: pandas
Requires-Dist: numpy
Requires-Dist: ndjson
Requires-Dist: tqdm
